README.rst
setup.cfg
setup.py
ddbgraphite/__init__.py
ddbgraphite/_version.py
ddbgraphite/listen.py
ddbgraphite.egg-info/PKG-INFO
ddbgraphite.egg-info/SOURCES.txt
ddbgraphite.egg-info/dependency_links.txt
ddbgraphite.egg-info/entry_points.txt
ddbgraphite.egg-info/not-zip-safe
ddbgraphite.egg-info/requires.txt
ddbgraphite.egg-info/top_level.txt
test/__init__.py