Metadata-Version: 1.1
Name: ddbgraphite
Version: 0.0.7
Summary: Dalmatiner Graphite
Home-page: https://github.com/dataloop/dalmatiner-graphite
Author: Steven Acreman
Author-email: steven.acreman@dataloop.io
License: Apache License, Version 2.0
Download-URL: https://github.com/dataloop/dalmatiner-graphite/tarball/v0.0.7
Keywords: dataloop dalmatiner
Platform: any
Classifier: Intended Audience :: Developers
Classifier: Intended Audience :: System Administrators
Classifier: License :: OSI Approved :: Apache Software License
